Metadata-Version: 1.2
Name: LiveCaptionLinux
Version: 1.0
Summary: Live Captions in Linux for Discord, Telegram, Google Meet, Slack, Skype etc.
Home-page: https://github.com/RonyMacfly/LiveCaptionLinux
Author: Rony Macfly
Author-email: rony.macfly@gmail.com
License: UNKNOWN
Platform: UNKNOWN
Requires-Python: >=3
